JavaHexinjishu36JiangLiyunhuaWan/README.md
JavaHexinjishu36JiangLiyunhuaWan/__init__.py
JavaHexinjishu36JiangLiyunhuaWan/__main__.py
JavaHexinjishu36JiangLiyunhuaWan/file.epub
JavaHexinjishu36JiangLiyunhuaWan/index.html
JavaHexinjishu36JiangLiyunhuaWan/css/__init__.py
JavaHexinjishu36JiangLiyunhuaWan/css/annotations.css
JavaHexinjishu36JiangLiyunhuaWan/css/main.css
JavaHexinjishu36JiangLiyunhuaWan/css/normalize.css
JavaHexinjishu36JiangLiyunhuaWan/css/popup.css
JavaHexinjishu36JiangLiyunhuaWan/font/__init__.py
JavaHexinjishu36JiangLiyunhuaWan/font/fontello.eot
JavaHexinjishu36JiangLiyunhuaWan/font/fontello.svg
JavaHexinjishu36JiangLiyunhuaWan/font/fontello.ttf
JavaHexinjishu36JiangLiyunhuaWan/font/fontello.woff
JavaHexinjishu36JiangLiyunhuaWan/img/__init__.py
JavaHexinjishu36JiangLiyunhuaWan/img/annotator-glyph-sprite.png
JavaHexinjishu36JiangLiyunhuaWan/img/annotator-icon-sprite.png
JavaHexinjishu36JiangLiyunhuaWan/img/apple-touch-icon.png
JavaHexinjishu36JiangLiyunhuaWan/img/cancelfullscreen.png
JavaHexinjishu36JiangLiyunhuaWan/img/close.png
JavaHexinjishu36JiangLiyunhuaWan/img/fullscreen.png
JavaHexinjishu36JiangLiyunhuaWan/img/loader.gif
JavaHexinjishu36JiangLiyunhuaWan/img/menu-icon.png
JavaHexinjishu36JiangLiyunhuaWan/img/save.png
JavaHexinjishu36JiangLiyunhuaWan/img/saved.png
JavaHexinjishu36JiangLiyunhuaWan/img/settings-s.png
JavaHexinjishu36JiangLiyunhuaWan/img/settings.png
JavaHexinjishu36JiangLiyunhuaWan/img/star.png
JavaHexinjishu36JiangLiyunhuaWan/js/__init__.py
JavaHexinjishu36JiangLiyunhuaWan/js/epub.js
JavaHexinjishu36JiangLiyunhuaWan/js/epub.min.js
JavaHexinjishu36JiangLiyunhuaWan/js/epub.min.map
JavaHexinjishu36JiangLiyunhuaWan/js/hooks.min.js
JavaHexinjishu36JiangLiyunhuaWan/js/hooks.min.map
JavaHexinjishu36JiangLiyunhuaWan/js/reader.js
JavaHexinjishu36JiangLiyunhuaWan/js/reader.js.map
JavaHexinjishu36JiangLiyunhuaWan/js/reader.min.js
JavaHexinjishu36JiangLiyunhuaWan/js/reader.min.map
JavaHexinjishu36JiangLiyunhuaWan/js/hooks/__init__.py
java_hexinjishu_36_jiang_liyunhua_wan-2024.3.3.0.dist-info/METADATA
java_hexinjishu_36_jiang_liyunhua_wan-2024.3.3.0.dist-info/WHEEL
java_hexinjishu_36_jiang_liyunhua_wan-2024.3.3.0.dist-info/entry_points.txt
java_hexinjishu_36_jiang_liyunhua_wan-2024.3.3.0.dist-info/top_level.txt
java_hexinjishu_36_jiang_liyunhua_wan-2024.3.3.0.dist-info/RECORD
